classes/__init__.py
classes/article_raw_en.py
classes/metadata_item_ner_en.py
starter_service/__init__.py
starter_service/api.py
starter_service/api_server.py
starter_service/avro_parser.py
starter_service/base_service.py
starter_service/env.py
starter_service/kafka_adapter.py
starter_service/schemas.py
starter_service/sub_process.py
starter_service/examples/__init__.py
starter_service/examples/error.py
starter_service/examples/manual_api.py
starter_service/examples/manual_kafka.py
starter_service/examples/multi.py
starter_service/examples/offset_kafka.py
starter_service/examples/single.py
starter_service/tests/__init__.py
starter_service/tests/employee.py
starter_service/tests/teet.py
starter_service/tests/test_avro_parser.py
starter_service/tests/tst.py
osint_python_starter_service-2.3.0.dist-info/LICENSE
osint_python_starter_service-2.3.0.dist-info/METADATA
osint_python_starter_service-2.3.0.dist-info/WHEEL
osint_python_starter_service-2.3.0.dist-info/top_level.txt
osint_python_starter_service-2.3.0.dist-info/RECORD
