Metadata-Version: 2.1
Name: osint-python-starter-service
Version: 2.3.0
Summary: Python starter service
Home-page: https://github.com/OSINT-VDU-TNO/python-starter-service
Author: mindpetk
Author-email: petkeviciusm@gmail.com
License: UNKNOWN
Platform: UNKNOWN
Classifier: Programming Language :: Python :: 3
Classifier: License :: OSI Approved :: MIT License
Classifier: Operating System :: OS Independent
License-File: LICENSE
Requires-Dist: pykafka
Requires-Dist: avro-python3
Requires-Dist: requests
Requires-Dist: environs
Requires-Dist: fastapi
Requires-Dist: uvicorn
Requires-Dist: pydantic
Requires-Dist: pydantic-avro
Requires-Dist: osint-python-test-bed-adapter
